py5paisa/__init__.py
py5paisa/auth.py
py5paisa/const.py
py5paisa/csv.py
py5paisa/logging.py
py5paisa/order.py
py5paisa/py5paisa.py
py5paisa/strategy.py
py5paisa/urlconst.py
py5paisa-0.7.21.2.dist-info/AUTHORS.rst
py5paisa-0.7.21.2.dist-info/METADATA
py5paisa-0.7.21.2.dist-info/WHEEL
py5paisa-0.7.21.2.dist-info/top_level.txt
py5paisa-0.7.21.2.dist-info/RECORD
