Metadata-Version: 2.1
Name: py5paisa
Version: 0.7.21.2
Summary: Python SDK for 5paisa APIs natively written in VB.NET
Home-page: https://github.com/5paisa/py5paisa
Author: 5paisa
Author-email: coreteam@5paisa.com
Keywords: py5paisa
Classifier: Development Status :: 2 - Pre-Alpha
Classifier: Intended Audience :: Developers
Classifier: Natural Language :: English
Classifier: Programming Language :: Python :: 3.6
Requires-Python: >=3.6
License-File: AUTHORS.rst
Requires-Dist: requests
Requires-Dist: pycryptodome>=3.9.8
Requires-Dist: certifi>=2020.4.5.1
Requires-Dist: chardet>=3.0.4
Requires-Dist: pbkdf2>=1.3
Requires-Dist: urllib3>=1.25.8
Requires-Dist: idna>=2.9
Requires-Dist: loguru>=0.5.1
Requires-Dist: websocket-client>=0.58.0
Requires-Dist: pandas>=1.2.4
Requires-Dist: pyjwt==2.3.0
Requires-Dist: httpx<0.29.0,>=0.28.1
